data_processing/__init__.py
data_processing/data_dealer.py
data_processing/__pycache__/__init__.cpython-39.pyc
data_processing/__pycache__/data_dealer.cpython-39.pyc
hierarchical_rag/__init__.py
hierarchical_rag_retrieval-0.1.2.dist-info/licenses/LICENSE
retrieval/RAGTree_function.py
retrieval/__init__.py
retrieval/generated_function.py
utils/__init__.py
utils/query_retrieval.py
utils/word_chunking.py
utils/word_embedding.py
hierarchical_rag_retrieval-0.1.2.dist-info/METADATA
hierarchical_rag_retrieval-0.1.2.dist-info/WHEEL
hierarchical_rag_retrieval-0.1.2.dist-info/top_level.txt
hierarchical_rag_retrieval-0.1.2.dist-info/RECORD
