Metadata-Version: 2.4
Name: hierarchical-rag-retrieval
Version: 0.1.2
Summary: AI-Powered Legal Document Retrieval Engine based on Hierarchical Clustering & RAG
Home-page: https://github.com/arthur422tp/hierarchical
Author: arthur422tp
Author-email: arthur422tp <arthur422tp@gmail.com>
License: MIT
Project-URL: Homepage, https://github.com/arthur422tp/hierarchical
Project-URL: Documentation, https://github.com/arthur422tp/hierarchical#readme
Project-URL: Repository, https://github.com/arthur422tp/hierarchical
Project-URL: Bug Tracker, https://github.com/arthur422tp/hierarchical/issues
Project-URL: arXiv Paper, https://arxiv.org/abs/2506.13607
Keywords: rag,retrieval,hierarchical,clustering,legal,nlp,ai,machine-learning
Classifier: Development Status :: 3 - Alpha
Classifier: Intended Audience :: Developers
Classifier: Intended Audience :: Science/Research
Classifier: Topic :: Scientific/Engineering :: Artificial Intelligence
Classifier: Topic :: Text Processing :: Linguistic
Classifier: License :: OSI Approved :: MIT License
Classifier: Programming Language :: Python :: 3
Classifier: Programming Language :: Python :: 3.8
Classifier: Programming Language :: Python :: 3.9
Classifier: Programming Language :: Python :: 3.10
Classifier: Programming Language :: Python :: 3.11
Classifier: Operating System :: OS Independent
Requires-Python: >=3.8
License-File: LICENSE
Requires-Dist: sentence-transformers>=2.2.0
Requires-Dist: faiss-cpu>=1.7.0
Requires-Dist: torch>=2.0.0
Requires-Dist: numpy>=2.3.0
Requires-Dist: scipy>=1.16.0
Requires-Dist: fastcluster>=1.3.0
Requires-Dist: scikit-learn>=1.3.0
Requires-Dist: langchain>=0.3.26
Requires-Dist: langchain-openai>=0.0.2
Requires-Dist: langchain_community>=0.0.10
Requires-Dist: python-dotenv>=1.0.0
Requires-Dist: pandas>=1.5.0
Provides-Extra: dev
Requires-Dist: pytest>=6.0; extra == "dev"
Requires-Dist: black; extra == "dev"
Requires-Dist: flake8; extra == "dev"
Requires-Dist: isort; extra == "dev"
Provides-Extra: app
Requires-Dist: fastapi>=0.104.0; extra == "app"
Requires-Dist: uvicorn>=0.24.0; extra == "app"
Requires-Dist: python-multipart>=0.0.6; extra == "app"
Requires-Dist: pydantic>=2.4.0; extra == "app"
Dynamic: author
Dynamic: home-page
Dynamic: license-file
Dynamic: requires-python
